{
  "chapter_title": "ಇತಿಹಾಸ ಪರಿಚಯ: ಶಿಲಾಯುಗ ಮತ್ತು ಲೋಹಯುಗ",
  "module_id": "m1",
  "module_title": "ಇತಿಹಾಸ: ಪರಿಕಲ್ಪನೆ ಮತ್ತು ಆಧಾರಗಳು",
  "target_exam": "GPSTR",
  "chunks": [
    {
      "chunk_id": "m1_c1",
      "order": 1,
      "chunk_type": "intro",
      "script": "<speak><mark name=\"m1_c1_p1\"/>ಖಂಡಿತ, ಸೂಚನೆಗಳನ್ನು ಕಟ್ಟುನಿಟ್ಟಾಗಿ ಪಾಲಿಸಿ, GPSTR ಆಕಾಂಕ್ಷಿಗಳಿಗಾಗಿ ಸೂಚಿಸಲಾದ ಅಧ್ಯಯನ ಸಾಮಗ್ರಿಯನ್ನು ಸಿದ್ಧಪಡಿಸಲಾಗಿದೆ.<break time=\"400ms\"/></speak>",
      "display": {
        "title": "ಪರಿಚಯ",
        "markdown": "[mark:m1_c1_p1] ಸೂಚನೆಗಳನ್ನು ಕಟ್ಟುನಿಟ್ಟಾಗಿ ಪಾಲಿಸಿ, GPSTR ಆಕಾಂಕ್ಷಿಗಳಿಗಾಗಿ ಸೂಚಿಸಲಾದ ಅಧ್ಯಯನ ಸಾಮಗ್ರಿಯನ್ನು ಸಿದ್ಧಪಡಿಸಲಾಗಿದೆ.",
        "equations": []
      },
      "visual": {
        "type": "none",
        "alt_text": "",
        "detailed_description": "",
        "future_asset_id": ""
      },
      "layout": "left_text_only",
      "animation": {
        "pause_after": 0.5
      }
    },
    {
      "chunk_id": "m1_c2",
      "order": 2,
      "chunk_type": "definition",
      "script": "<speak><mark name=\"m1_c2_p1\"/>ಇತಿಹಾಸವು ಕೇವಲ ಗತಕಾಲದ ಕಥೆಗಳ ಸಂಗ್ರಹವಲ್ಲ.<break time=\"400ms\"/><mark name=\"m1_c2_p2\"/>ಬದಲಾಗಿ, ಇದು ಗತಕಾಲದಲ್ಲಿ ಜರುಗಿದ ಘಟನೆಗಳ ಕ್ರಮಬದ್ಧ ಮತ್ತು ವೈಜ್ಞಾನಿಕ ಅಧ್ಯಯನವಾಗಿದೆ.<break time=\"400ms\"/><mark name=\"m1_c2_p3\"/>ಈ ಅಧ್ಯಯನವು ನಿಖರತೆ ಮತ್ತು ಖಚಿತತೆಯನ್ನು ಆಧರಿಸಿರುತ್ತದೆ.<break time=\"400ms\"/><mark name=\"m1_c2_p4\"/>ಇತಿಹಾಸವನ್ನು ಕಥೆಯಿಂದ ಪ್ರತ್ಯೇಕಿಸುವ ಪ್ರಮುಖ ಅಂಶಗಳೆಂದರೆ ಕಾಲ, ಸ್ಥಳ, ಮತ್ತು ವ್ಯಕ್ತಿಗಳ ಕುರಿತಾದ ನಿರ್ದಿಷ್ಟತೆ.<break time=\"400ms\"/></speak>",
      "display": {
        "title": "ಇತಿಹಾಸದ ಪರಿಕಲ್ಪನೆ",
        "markdown": "[mark:m1_c2_p1] ಇತಿಹಾಸವು ಕೇವಲ ಗತಕಾಲದ ಕಥೆಗಳ ಸಂಗ್ರಹವಲ್ಲ.\n[mark:m1_c2_p2] ಗತಕಾಲದಲ್ಲಿ ಜರುಗಿದ ಘಟನೆಗಳ ಕ್ರಮಬದ್ಧ ಮತ್ತು ವೈಜ್ಞಾನಿಕ ಅಧ್ಯಯನವಾಗಿದೆ.\n[mark:m1_c2_p3] ಅಧ್ಯಯನವು ನಿಖರತೆ ಮತ್ತು ಖಚಿತತೆಯನ್ನು ಆಧರಿಸಿರುತ್ತದೆ.\n[mark:m1_c2_p4] ಇತಿಹಾಸವನ್ನು ಕಥೆಯಿಂದ ಪ್ರತ್ಯೇಕಿಸುವ ಪ್ರಮುಖ ಅಂಶಗಳು: ಕಾಲ, ಸ್ಥಳ, ವ್ಯಕ್ತಿ.",
        "equations": []
      },
      "visual": {
        "type": "none",
        "alt_text": "",
        "detailed_description": "",
        "future_asset_id": ""
      },
      "layout": "left_text_only",
      "animation": {
        "pause_after": 0.5
      }
    },
    {
      "chunk_id": "m1_c3",
      "order": 3,
      "chunk_type": "concept_explanation",
      "script": "<speak><mark name=\"m1_c3_p1\"/>ಕಥೆ: \"ಒಂದಾನೊಂದು ಊರಿನಲ್ಲಿ ಒಬ್ಬ ರಾಜ ಯುದ್ಧ ಮಾಡಿದ.\" - ಇದು ಅಸ್ಪಷ್ಟ ಮತ್ತು ಸಾಮಾನ್ಯ ನಿರೂಪಣೆ.<break time=\"400ms\"/><mark name=\"m1_c3_p2\"/>ಇತಿಹಾಸ: \"ಸಾ.ಶ.ಪೂ. 261ರಲ್ಲಿ ಪಾಟಲೀಪುತ್ರದ ಮೌರ್ಯ ದೊರೆ ಅಶೋಕನು ಕಳಿಂಗ ರಾಜ್ಯದ ಮೇಲೆ ಯುದ್ಧ ಮಾಡಿದ.\" - ಇದು ಕಾಲ (ಸಾ.ಶ.ಪೂ. 261), ಸ್ಥಳ (ಪಾಟಲೀಪುತ್ರ, ಕಳಿಂಗ) ಮತ್ತು ವ್ಯಕ್ತಿ (ಅಶೋಕ) ಕುರಿತು ನಿರ್ದಿಷ್ಟ ಮಾಹಿತಿ ನೀಡುವುದರಿಂದ ಐತಿಹಾಸಿಕ ನಿರೂಪಣೆಯಾಗುತ್ತದೆ.<break time=\"400ms\"/></speak>",
      "display": {
        "title": "ಕಥೆ ಮತ್ತು ಇತಿಹಾಸದ ವ್ಯತ್ಯಾಸ",
        "markdown": "[mark:m1_c3_p1] ಕಥೆ: \"ಒಂದಾನೊಂದು ಊರಿನಲ್ಲಿ ಒಬ್ಬ ರಾಜ ಯುದ್ಧ ಮಾಡಿದ.\" - ಅಸ್ಪಷ್ಟ ನಿರೂಪಣೆ.\n[mark:m1_c3_p2] ಇತಿಹಾಸ: \"ಸಾ.ಶ.ಪೂ. 261ರಲ್ಲಿ ಪಾಟಲೀಪುತ್ರದ ಮೌರ್ಯ ದೊರೆ ಅಶೋಕನು ಕಳಿಂಗ ರಾಜ್ಯದ ಮೇಲೆ ಯುದ್ಧ ಮಾಡಿದ.\" - ನಿರ್ದಿಷ್ಟ ಮಾಹಿತಿ.",
        "equations": []
      },
      "visual": {
        "type": "placeholder",
        "alt_text": "ಕಥೆ ಮತ್ತು ಇತಿಹಾಸದ ನಿರೂಪಣೆಯ ತಾರತಮ್ಯ",
        "detailed_description": "Comparison chart: Left side - ಸಾಮಾನ್ಯ ಕಥೆ (ಅಸ್ಪಷ್ಟ ಕಾಲ, ಸ್ಥಳ, ವ್ಯಕ್ತಿ); Right side - ಇತಿಹಾಸ (ನಿರ್ದಿಷ್ಟ ಕಾಲ, ಸ್ಥಳ, ವ್ಯಕ್ತಿ).",
        "future_asset_id": ""
      },
      "layout": "left_text_right_visual",
      "animation": {
        "pause_after": 0.5
      }
    },
    {
      "chunk_id": "m1_c4",
      "order": 4,
      "chunk_type": "concept_explanation",
      "script": "<speak><mark name=\"m1_c4_p1\"/>ಗ್ರೀಕ್ ಇತಿಹಾಸಕಾರ ಹೆರೊಡೋಟಸ್, ತನ್ನ ಕೃತಿಗಳಲ್ಲಿ ಅಳವಡಿಸಿಕೊಂಡ ವೈಜ್ಞಾನಿಕ ಮತ್ತು ಕ್ರಮಬದ್ಧ ನಿರೂಪಣಾ ಶೈಲಿಯ ಕಾರಣದಿಂದಾಗಿ 'ಇತಿಹಾಸದ ಪಿತಾಮಹ' ಎಂದು ಗೌರವಿಸಲ್ಪಟ್ಟಿದ್ದಾನೆ.<break time=\"400ms\"/></speak>",
      "display": {
        "title": "ಹೆರೊಡೋಟಸ್",
        "markdown": "[mark:m1_c4_p1] ಗ್ರೀಕ್ ಇತಿಹಾಸಕಾರ ಹೆರೊಡೋಟಸ್, ವೈಜ್ಞಾನಿಕ ಮತ್ತು ಕ್ರಮಬದ್ಧ ನಿರೂಪಣಾ ಶೈಲಿಯಿಂದ 'ಇತಿಹಾಸದ ಪಿತಾಮಹ'.",
        "equations": []
      },
      "visual": {
        "type": "none",
        "alt_text": "",
        "detailed_description": "",
        "future_asset_id": ""
      },
      "layout": "left_text_only",
      "animation": {
        "pause_after": 0.5
      }
    },
    {
      "chunk_id": "m1_c5",
      "order": 5,
      "chunk_type": "concept_explanation",
      "script": "<speak><mark name=\"m1_c5_p1\"/>ಇತಿಹಾಸ ಅಧ್ಯಯನದ ಮಹತ್ವ:<break time=\"400ms\"/><mark name=\"m1_c5_p2\"/>ಇತಿಹಾಸದ ಅಧ್ಯಯನವು ಒಂದು ಸಮಾಜಕ್ಕೆ ಅತ್ಯಂತ ಅವಶ್ಯಕವಾಗಿದೆ.<break time=\"400ms\"/><mark name=\"m1_c5_p3\"/>ಇದು ಸಮಾಜದ ಸಾಮೂಹಿಕ ಸ್ಮರಣಶಕ್ತಿಯಾಗಿ ಕಾರ್ಯನಿರ್ವಹಿಸುತ್ತದೆ.<break time=\"400ms\"/><mark name=\"m1_c5_p4\"/>ಹಿಂದಿನ ತಲೆಮಾರುಗಳು ಮಾಡಿದ ತಪ್ಪುಗಳಿಂದ ಪಾಠ ಕಲಿಯಲು ಸಹಾಯ ಮಾಡುತ್ತದೆ.<break time=\"400ms\"/><mark name=\"m1_c5_p5\"/>ಹಿಂದಿನವರ ಯಶಸ್ಸಿನಿಂದ ಸ್ಫೂರ್ತಿ ಪಡೆಯಲು ಪ್ರೇರೇಪಿಸುತ್ತದೆ.<break time=\"400ms\"/><mark name=\"m1_c5_p6\"/>ನಮ್ಮ ಸಾಂಸ್ಕೃತಿಕ ಪರಂಪರೆಯ ಬಗ್ಗೆ ಅಭಿಮಾನ ಮತ್ತು ಗೌರವವನ್ನು ಮೂಡಿಸುತ್ತದೆ.<break time=\"400ms\"/></speak>",
      "display": {
        "title": "ಇತಿಹಾಸ ಅಧ್ಯಯನದ ಮಹತ್ವ",
        "markdown": "[mark:m1_c5_p3] ಸಮಾಜದ ಸಾಮೂಹಿಕ ಸ್ಮರಣಶಕ್ತಿ.\n[mark:m1_c5_p4] ತಪ್ಪುಗಳಿಂದ ಪಾಠ ಕಲಿಯಲು ಸಹಾಯ.\n[mark:m1_c5_p5] ಯಶಸ್ಸಿನಿಂದ ಸ್ಫೂರ್ತಿ.\n[mark:m1_c5_p6] ಸಾಂಸ್ಕೃತಿಕ ಪರಂಪರೆಯ ಬಗ್ಗೆ ಅಭಿಮಾನ.",
        "equations": []
      },
      "visual": {
        "type": "none",
        "alt_text": "",
        "detailed_description": "",
        "future_asset_id": ""
      },
      "layout": "left_text_only",
      "animation": {
        "pause_after": 0.5
      }
    },
    {
      "chunk_id": "m1_c6",
      "order": 6,
      "chunk_type": "definition",
      "script": "<speak><mark name=\"m1_c6_p1\"/>ಗತಕಾಲದ ಘಟನೆಗಳನ್ನು ವೈಜ್ಞಾನಿಕವಾಗಿ ಪುನರ್‌ರಚಿಸಲು ಇತಿಹಾಸಕಾರರು ಬಳಸುವ ಮೂಲ ಸಾಮಗ್ರಿಗಳನ್ನು 'ಆಧಾರಗಳು' ಎಂದು ಕರೆಯಲಾಗುತ್ತದೆ.<break time=\"400ms\"/><mark name=\"m1_c6_p2\"/>ಆಧಾರಗಳಿಲ್ಲದೆ ಇತಿಹಾಸವನ್ನು ರಚಿಸುವುದು ಅಸಾಧ್ಯ.<break time=\"400ms\"/><mark name=\"m1_c6_p3\"/>ಈ ಆಧಾರಗಳನ್ನು ಪ್ರಮುಖವಾಗಿ ಎರಡು ವಿಧಗಳಾಗಿ ವರ್ಗೀಕರಿಸಬಹುದು.<break time=\"400ms\"/></speak>",
      "display": {
        "title": "ಇತಿಹಾಸದ ಆಧಾರಗಳು",
        "markdown": "[mark:m1_c6_p1] ಮೂಲ ಸಾಮಗ್ರಿಗಳನ್ನು 'ಆಧಾರಗಳು' ಎಂದು ಕರೆಯಲಾಗುತ್ತದೆ.\n[mark:m1_c6_p2] ಆಧಾರಗಳಿಲ್ಲದೆ ಇತಿಹಾಸವನ್ನು ರಚಿಸುವುದು ಅಸಾಧ್ಯ.\n[mark:m1_c6_p3] ಆಧಾರಗಳ ಎರಡು ವಿಧಗಳು.",
        "equations": []
      },
      "visual": {
        "type": "placeholder",
        "alt_text": "ಇತಿಹಾಸದ ಆಧಾರಗಳ ವರ್ಗೀಕರಣ",
        "detailed_description": "Classification tree: ಇತಿಹಾಸದ ಆಧಾರಗಳು → 1. ಸಾಹಿತ್ಯ ಆಧಾರಗಳು, 2. ಪುರಾತತ್ವ ಆಧಾರಗಳು.",
        "future_asset_id": ""
      },
      "layout": "left_text_right_visual",
      "animation": {
        "pause_after": 0.5
      }
    },
    {
      "chunk_id": "m1_c7",
      "order": 7,
      "chunk_type": "structure_explanation",
      "script": "<speak><mark name=\"m1_c7_p1\"/>ಸಾಹಿತ್ಯ ಆಧಾರಗಳು: ಬರವಣಿಗೆಯ ರೂಪದಲ್ಲಿ ಅಥವಾ ತಲೆಮಾರುಗಳಿಂದ வாய್ಮொழಿ ಮೂಲಕ ಹರಿದು ಬಂದಿರುವ ಆಕರಗಳಿವು.<break time=\"400ms\"/><mark name=\"m1_c7_p2\"/>ಲಿಖಿತ ಸಾಹಿತ್ಯ: ಸ್ಥಳೀಯ ವಿದ್ವಾಂಸರು ಮತ್ತು ಲೇಖಕರು ತಮ್ಮ ನಾಡಿನ ಭಾಷೆಗಳಲ್ಲಿ ರಚಿಸಿದ ಕೃತಿಗಳು. ಇವು ಆ ಕಾಲದ ಆಡಳಿತ, ಸಮಾಜ ಮತ್ತು ಸಂಸ್ಕೃತಿಯ ಮೇಲೆ ಬೆಳಕು ಚೆಲ್ಲುತ್ತವೆ.<break time=\"400ms\"/><mark name=\"m1_c7_p3\"/>ಉದಾಹರಣೆ: ಕೌಟಿಲ್ಯನ 'ಅರ್ಥಶಾಸ್ತ್ರ', ಬಾಣಭಟ್ಟನ 'ಹರ್ಷಚರಿತ'.<break time=\"400ms\"/><mark name=\"m1_c7_p4\"/>ವಿದೇಶಿ ಸಾಹಿತ್ಯ: ಭಾರತಕ್ಕೆ ಭೇಟಿ ನೀಡಿದ ವಿದೇಶಿ ಪ್ರವಾಸಿಗರು, ರಾಯಭಾರಿಗಳು ಮತ್ತು ವ್ಯಾಪಾರಿಗಳು ತಮ್ಮ ಅನುಭವಗಳನ್ನು ದಾಖಲಿಸಿದ ಕೃತಿಗಳು. ಇವು ಸಮಕಾಲೀನ ಭಾರತದ ಬಗ್ಗೆ ಹೊರಗಿನವರ ದೃಷ್ಟಿಕೋನವನ್ನು ಒದಗಿಸುತ್ತವೆ.<break time=\"400ms\"/><mark name=\"m1_c7_p5\"/>ಉದಾಹರಣೆ: ಗ್ರೀಕ್ ರಾಯಭಾರಿ ಮೆಗಾಸ್ತನೀಸ್ ಬರೆದ 'ಇಂಡಿಕಾ', ಚೀನೀ ಯಾತ್ರಿಕ ಹ್ಯುಯೆನ್ ತ್ಸಾಂಗ್ ಬರೆದ 'ಸಿ-ಯು-ಕಿ'.<break time=\"400ms\"/><mark name=\"m1_c7_p6\"/>ಮೌಖಿಕ ಸಾಹಿತ್ಯ: ಯಾವುದೇ ಲಿಖಿತ ರೂಪವಿಲ್ಲದೆ, ಒಂದು ತಲೆಮಾರಿನಿಂದ ಇನ್ನೊಂದು ತಲೆಮಾರಿಗೆ வாய್ಮொழಿ ಮೂಲಕ ವರ್ಗಾಯಿಸಲ್ಪಟ್ಟ ಜ್ಞಾನ ಮತ್ತು ಕಥನಗಳು. ಇವು ಜನಸಾಮಾನ್ಯರ ಭಾವನೆಗಳು, ನಂಬಿಕೆಗಳು ಮತ್ತು ಸಾಮಾಜಿಕ ಜೀವನವನ್ನು ಪ್ರತಿಬಿಂಬಿಸುತ್ತವೆ.<break time=\"400ms\"/><mark name=\"m1_c7_p7\"/>ಉದಾಹರಣೆ: ಜನಪದ ಗೀತೆಗಳು, ಲಾವಣಿಗಳು, ಐತಿಹ್ಯಗಳು, ಮತ್ತು ಸ್ಥಳೀಯ ಕಥೆಗಳು.<break time=\"400ms\"/></speak>",
      "display": {
        "title": "ಸಾಹಿತ್ಯ ಆಧಾರಗಳ ವರ್ಗೀಕರಣ",
        "markdown": "[mark:m1_c7_p2] ಲಿಖಿತ ಸಾಹಿತ್ಯ: ಸ್ಥಳೀಯ ವಿದ್ವಾಂಸರು ಮತ್ತು ಲೇಖಕರು ರಚಿಸಿದ ಕೃತಿಗಳು.\n[mark:m1_c7_p4] ವಿದೇಶಿ ಸಾಹಿತ್ಯ: ಪ್ರವಾಸಿಗರು, ರಾಯಭಾರಿಗಳು, ವ್ಯಾಪಾರಿಗಳ ಅನುಭವಗಳು.\n[mark:m1_c7_p6] ಮೌಖಿಕ ಸಾಹಿತ್ಯ: ತಲೆಮಾರುಗಳಿಂದ ಹರಿದು ಬಂದ ಜ್ಞಾನ ಮತ್ತು ಕಥನಗಳು.\n[mark:m1_c7_p7] ಉದಾಹರಣೆ: ಜನಪದ ಗೀತೆಗಳು, ಲಾವಣಿಗಳು, ಐತಿಹ್ಯಗಳು.",
        "equations": []
      },
      "visual": {
        "type": "placeholder",
        "alt_text": "ಸಾಹಿತ್ಯ ಆಧಾರಗಳ ಉಪವರ್ಗಗಳು",
        "detailed_description": "Hierarchy: ಸಾಹಿತ್ಯ ಆಧಾರಗಳು → ಲಿಖಿತ ಸಾಹಿತ್ಯ (ದೇಶೀಯ, ವಿದೇಶಿ), ಮೌಖಿಕ ಸಾಹಿತ್ಯ.",
        "future_asset_id": ""
      },
      "layout": "left_text_right_visual",
      "animation": {
        "pause_after": 0.5
      }
    },
    {
      "chunk_id": "m1_c8",
      "order": 8,
      "chunk_type": "structure_explanation",
      "script": "<speak><mark name=\"m1_c8_p1\"/>ಪುರಾತತ್ವ ಆಧಾರಗಳು: ಭೂಮಿಯ ಉತ್ಖನನದ (ಅಗೆತ) ಮೂಲಕ ದೊರೆತ ಭೌತಿಕ ಅವಶೇಷಗಳು ಪುರಾತತ್ವ ಆಧಾರಗಳಾಗಿವೆ.<break time=\"400ms\"/><mark name=\"m1_c8_p2\"/>ಇವು ಗತಕಾಲದ ಮಾನವ ಜೀವನ ಮತ್ತು ಸಂಸ್ಕೃತಿಯ ನೇರ ಸಾಕ್ಷಿಗಳಾಗಿವೆ.<break time=\"400ms\"/><mark name=\"m1_c8_p3\"/>ಶಾಸನಗಳು: ಕಲ್ಲು, ಬಂಡೆ, ಲೋಹದ ತಗಡುಗಳು ಅಥವಾ ದೇವಾಲಯದ ಗೋಡೆಗಳ ಮೇಲೆ ಕೆತ್ತಲಾದ ಬರಹಗಳು. ಇವು ರಾಜರ ಆಜ್ಞೆಗಳು, ದಾನ-ದತ್ತಿಗಳು ಅಥವಾ ಸಾಧನೆಗಳನ್ನು ದಾಖಲಿಸುತ್ತವೆ.<break time=\"400ms\"/><mark name=\"m1_c8_p4\"/>ನಾಣ್ಯಗಳು: ಇವು ಕೇವಲ ವಿನಿಮಯ ಮಾಧ್ಯಮವಲ್ಲ, ಬದಲಾಗಿ ಇತಿಹಾಸದ ಪ್ರಮುಖ ಆಕರಗಳಾಗಿವೆ. ನಾಣ್ಯಗಳು ಆಯಾ ಕಾಲದ ರಾಜಮನೆತನ, ಆರ್ಥಿಕ ಸ್ಥಿತಿ, ಧರ್ಮ, ಮತ್ತು ಲೋಹಶಾಸ್ತ್ರದ ಜ್ಞಾನದ ಬಗ್ಗೆ ಅಮೂಲ್ಯ ಮಾಹಿತಿ ನೀಡುತ್ತವೆ.<break time=\"400ms\"/><mark name=\"m1_c8_p5\"/>ಸ್ಮಾರಕಗಳು: ಅಂದಿನ ಕಾಲದ ವಾಸ್ತುಶಿಲ್ಪ, ತಂತ್ರಜ್ಞಾನ ಮತ್ತು ಕಲಾತ್ಮಕ ಕೌಶಲ್ಯಕ್ಕೆ ಸಾಕ್ಷಿಯಾಗಿ ನಿಲ್ಲುವ ನಿರ್ಮಾಣಗಳು.<break time=\"400ms\"/><mark name=\"m1_c8_p6\"/>ಉದಾಹರಣೆ: ಕಟ್ಟಡಗಳು, ದೇವಾಲಯಗಳು, ಕೋಟೆಗಳು, ಸ್ತೂಪಗಳು.<break time=\"400ms\"/><mark name=\"m1_c8_p7\"/>ಇತರ ಅವಶೇಷಗಳು: ಉತ್ಖನನದಲ್ಲಿ ದೊರೆತ ಇತರೆ ವಸ್ತುಗಳು.<break time=\"400ms\"/><mark name=\"m1_c8_p8\"/>ಉದಾಹರಣೆ: ಮಡಿಕೆ ಚೂರುಗಳು, ಕಲ್ಲಿನ ಅಥವಾ ಲೋಹದ ಉಪಕರಣಗಳು, ಆಭರಣಗಳು, ಮತ್ತು ಜೀವಿಗಳ ಪಳೆಯುಳಿಕೆಗಳು.<break time=\"400ms\"/></speak>",
      "display": {
        "title": "ಪುರಾತತ್ವ ಆಧಾರಗಳ ವರ್ಗೀಕರಣ",
        "markdown": "[mark:m1_c8_p3] ಶಾಸನಗಳು: ಕೆತ್ತಲಾದ ಬರಹಗಳು.\n[mark:m1_c8_p4] ನಾಣ್ಯಗಳು: ರಾಜಮನೆತನ, ಆರ್ಥಿಕ ಸ್ಥಿತಿ, ಧರ್ಮದ ಮಾಹಿತಿ.\n[mark:m1_c8_p5] ಸ್ಮಾರಕಗಳು: ವಾಸ್ತುಶಿಲ್ಪ, ತಂತ್ರಜ್ಞಾನ, ಕೌಶಲ್ಯ.\n[mark:m1_c8_p7] ಇತರ ಅವಶೇಷಗಳು: ಮಡಿಕೆ, ಉಪಕರಣಗಳು, ಆಭರಣಗಳು.",
        "equations": []
      },
      "visual": {
        "type": "placeholder",
        "alt_text": "ಪುರಾತತ್ವ ಆಧಾರಗಳ ಉಪವರ್ಗಗಳು",
        "detailed_description": "Hierarchy: ಪುರಾತತ್ವ ಆಧಾರಗಳು → ಶಾಸನಗಳು, ನಾಣ್ಯಗಳು, ಸ್ಮಾರಕಗಳು, ಇತರ ಅವಶೇಷಗಳು.",
        "future_asset_id": ""
      },
      "layout": "left_text_right_visual",
      "animation": {
        "pause_after": 0.5
      }
    },
    {
      "chunk_id": "m1_c9",
      "order": 9,
      "chunk_type": "structure_explanation",
      "script": "<speak><mark name=\"m1_c9_p1\"/>ಇತಿಹಾಸ ರಚನೆಯಲ್ಲಿ ಸಾಹಿತ್ಯ ಮತ್ತು ಪುರಾತತ್ವ ಆಧಾರಗಳೆರಡೂ ಮುಖ್ಯವಾದರೂ, ಅವುಗಳ ವಿಶ್ವಾಸಾರ್ಹತೆಯಲ್ಲಿ ವ್ಯತ್ಯಾಸಗಳಿವೆ.<break time=\"400ms\"/><mark name=\"m1_c9_p2\"/>ಪುರಾತತ್ವ ಆಧಾರಗಳ ವಸ್ತುನಿಷ್ಠತೆ: ಪುರಾತತ್ವ ಆಧಾರಗಳನ್ನು (ಶಾಸನ, ನಾಣ್ಯ, ಸ್ಮಾರಕ) ಸಾಹಿತ್ಯ ಆಧಾರಗಳಿಗಿಂತ ಹೆಚ್ಚು ವಸ್ತುನಿಷ್ಠ (objective) ಮತ್ತು ವಿಶ್ವಾಸಾರ್ಹ ಎಂದು ಪರಿಗಣಿಸಲಾಗುತ್ತದೆ. ಇದರ ಮುಖ್ಯ ಕಾರಣವೆಂದರೆ, ಇವುಗಳನ್ನು ಸೃಷ್ಟಿಸಿದ ನಂತರ ಸುಲಭವಾಗಿ ತಿರುಚಲು ಅಥವಾ ಬದಲಾಯಿಸಲು ಸಾಧ್ಯವಿಲ್ಲ.<break time=\"400ms\"/><mark name=\"m1_c9_p3\"/>ಸಾಹಿತ್ಯ ಆಧಾರಗಳ ಮಿತಿಗಳು: ಸಾಹಿತ್ಯ ಆಧಾರಗಳು ಲೇಖಕರ ವೈಯಕ್ತಿಕ ದೃಷ್ಟಿಕೋನ, ಅತಿಶಯೋಕ್ತಿ ಅಥವಾ ಪೂರ್ವಾಗ್ರಹಗಳಿಂದ ಪ್ರಭಾವಿತವಾಗಿರುವ ಸಾಧ್ಯತೆ ಇರುತ್ತದೆ. ಲೇಖಕನು ತನ್ನ ಆಶ್ರಯದಾತನನ್ನು ಹೊಗಳಬಹುದು ಅಥವಾ ಶತ್ರುಗಳನ್ನು ತೆಗಳಬಹುದು.<break time=\"400ms\"/><mark name=\"m1_c9_p4\"/>ವೈಜ್ಞಾನಿಕ ವಿಧಾನ: ಒಬ್ಬ ನಿಪುಣ ಇತಿಹಾಸಕಾರನು ಯಾವುದೇ ಒಂದು ಬಗೆಯ ಆಧಾರವನ್ನು ಮಾತ್ರ ಅವಲಂಬಿಸುವುದಿಲ್ಲ. ಬದಲಾಗಿ, ಎರಡೂ ಬಗೆಯ ಆಧಾರಗಳನ್ನು ತುಲನಾತ್ಮಕವಾಗಿ ವಿಮರ್ಶಿಸಿ, ಅವುಗಳಲ್ಲಿನ ಮಾಹಿತಿಯನ್ನು ಪರಸ್ಪರ ತಾಳೆ ನೋಡಿ, ಸತ್ಯಾಂಶವನ್ನು ಖಚಿತಪಡಿಸಿಕೊಂಡು ಇತಿಹಾಸವನ್ನು ಪುನರ್‌ರಚಿಸುತ್ತಾನೆ. ಇದೇ ಇತಿಹಾಸ ರಚನೆಯ ವೈಜ್ಞಾನಿಕ ವಿಧಾನವಾಗಿದೆ.<break time=\"400ms\"/></speak>",
      "display": {
        "title": "ಆಧಾರಗಳ ತುಲನಾತ್ಮಕ ವಿಶ್ಲೇಷಣೆ",
        "markdown": "[mark:m1_c9_p2] ಪುರಾತತ್ವ ಆಧಾರಗಳು ಹೆಚ್ಚು ವಸ್ತುನಿಷ್ಠ ಮತ್ತು ವಿಶ್ವಾಸಾರ್ಹ.\n[mark:m1_c9_p3] ಸಾಹಿತ್ಯ ಆಧಾರಗಳು ವೈಯಕ್ತಿಕ ದೃಷ್ಟಿಕೋನದಿಂದ ಪ್ರಭಾವಿತ.\n[mark:m1_c9_p4] ನಿಪುಣ ಇತಿಹಾಸಕಾರನು ಎರಡೂ ಆಧಾರಗಳನ್ನು ವಿಮರ್ಶಿಸಿ, ಸತ್ಯಾಂಶವನ್ನು ಖಚಿತಪಡಿಸುತ್ತಾನೆ.",
        "equations": []
      },
      "visual": {
        "type": "placeholder",
        "alt_text": "ಸಾಹಿತ್ಯ ಮತ್ತು ಪುರಾತತ್ವ ಆಧಾರಗಳ ತುಲನಾತ್ಮಕ ವಿಶ್ಲೇಷಣೆ",
        "detailed_description": "Comparison table: ಪುರಾತತ್ವ ಆಧಾರಗಳು (objectivity, reliability, immutable) vs ಸಾಹಿತ್ಯ ಆಧಾರಗಳು (subjectivity, bias, exaggeration). Arrow to: ವೈಜ್ಞಾನಿಕ ವಿಧಾನ (combining both sources).",
        "future_asset_id": ""
      },
      "layout": "left_text_right_visual",
      "animation": {
        "pause_after": 0.5
      }
    },
    {
      "chunk_id": "m1_c10",
      "order": 10,
      "chunk_type": "concept_explanation",
      "script": "<speak><mark name=\"m1_c10_p1\"/>ಈ ಘಟಕದಲ್ಲಿ ಕಲಿತ ಆಧಾರಗಳ ಬಗೆಗಿನ ತಿಳುವಳಿಕೆಯು ಇತಿಹಾಸದ ಮುಂದಿನ ಅಧ್ಯಯನಕ್ಕೆ ಬುನಾದಿಯಾಗಿದೆ.<break time=\"400ms\"/><mark name=\"m1_c10_p2\"/>ನಿರ್ದಿಷ್ಟವಾಗಿ, ಪ್ರಾಗೈತಿಹಾಸಿಕ ಕಾಲ (Prehistoric Period) ಮತ್ತು ಐತಿಹಾಸಿಕ ಕಾಲ (Historic Period) ಗಳ ನಡುವಿನ ವ್ಯತ್ಯಾಸವನ್ನು ಗ್ರಹಿಸಲು ಇದು ಅತ್ಯಗತ್ಯ.<break time=\"400ms\"/><mark name=\"m1_c10_p3\"/>ಅಕ್ಷರ ಜ್ಞಾನದ ಇರುವಿಕೆ ಅಥವಾ ಅನುಪಸ್ಥಿತಿಯು ಲಭ್ಯವಿರುವ ಆಧಾರಗಳ ಸ್ವರೂಪವನ್ನು ನಿರ್ಧರಿಸುತ್ತದೆ, ಮತ್ತು ಇದೇ ಈ ಎರಡು ಕಾಲಘಟ್ಟಗಳನ್ನು ವಿಭಜಿಸುವ ಪ್ರಮುಖ ಮಾನದಂಡವಾಗಿದೆ.<break time=\"400ms\"/></speak>",
      "display": {
        "title": "ಆಧಾರಗಳ ಅನ್ವಯ ಮತ್ತು ಸಂಬಂಧ",
        "markdown": "[mark:m1_c10_p1] ಕಲಿತ ಆಧಾರಗಳ ತಿಳುವಳಿಕೆ ಮುಂದಿನ ಅಧ್ಯಯನಕ್ಕೆ ಬುನಾದಿ.\n[mark:m1_c10_p2] ಪ್ರಾಗೈತಿಹಾಸಿಕ ಮತ್ತು ಐತಿಹಾಸಿಕ ಕಾಲಗಳ ವ್ಯತ್ಯಾಸವನ್ನು ಗ್ರಹಿಸಲು ಅಗತ್ಯ.\n[mark:m1_c10_p3] ಅಕ್ಷರ ಜ್ಞಾನದ ಇರುವಿಕೆ/ಅನುಪಸ್ಥಿತಿ ಕಾಲಘಟ್ಟ ವಿಭಜನೆಗೆ ಮಾನದಂಡ.",
        "equations": []
      },
      "visual": {
        "type": "placeholder",
        "alt_text": "ಪ್ರಾಗೈತಿಹಾಸಿಕ ಮತ್ತು ಐತಿಹಾಸಿಕ ಕಾಲಗಳ ವಿಭಜನೆ",
        "detailed_description": "Flowchart: ಅಕ್ಷರ ಜ್ಞಾನ ಇಲ್ಲ → ಪ್ರಾಗೈತಿಹಾಸಿಕ ಕಾಲ; ಅಕ್ಷರ ಜ್ಞಾನ ಇದೆ → ಐತಿಹಾಸಿಕ ಕಾಲ.",
        "future_asset_id": ""
      },
      "layout": "left_text_right_visual",
      "animation": {
        "pause_after": 0.5
      }
    }
  ]
}